[{"timestamp":"2025-12-21T00:00:00.000Z","count":3,"uniques":1},{"timestamp":"2025-12-22T01:40:57.226Z","count":0,"uniques":0},{"timestamp":"2025-12-23T01:27:12.010Z","count":0,"uniques":0},{"timestamp":"2025-12-24T01:26:12.755Z","count":0,"uniques":0},{"timestamp":"2025-12-25T00:00:00.000Z","count":1,"uniques":1},{"timestamp":"2025-12-26T00:00:00.000Z","count":1,"uniques":1},{"timestamp":"2025-12-27T01:25:30.497Z","count":0,"uniques":0},{"timestamp":"2025-12-28T01:45:51.502Z","count":0,"uniques":0},{"timestamp":"2025-12-29T01:44:32.911Z","count":0,"uniques":0},{"timestamp":"2025-12-30T01:27:49.382Z","count":0,"uniques":0},{"timestamp":"2025-12-31T00:00:00.000Z","count":3,"uniques":1},{"timestamp":"2026-01-01T00:00:00.000Z","count":1,"uniques":1},{"timestamp":"2026-01-02T00:00:00.000Z","count":1,"uniques":1},{"timestamp":"2026-01-03T00:00:00.000Z","count":1,"uniques":1},{"timestamp":"2026-01-04T00:00:00.000Z","count":1,"uniques":1},{"timestamp":"2026-01-05T01:47:08.567Z","count":0,"uniques":0},{"timestamp":"2026-01-06T01:39:12.628Z","count":0,"uniques":0},{"timestamp":"2026-01-07T00:00:00.000Z","count":1,"uniques":1},{"timestamp":"2026-01-08T00:00:00.000Z","count":1,"uniques":1},{"timestamp":"2026-01-09T01:39:37.761Z","count":0,"uniques":0},{"timestamp":"2026-01-10T00:00:00.000Z","count":1,"uniques":1},{"timestamp":"2026-01-11T00:00:00.000Z","count":1,"uniques":1},{"timestamp":"2026-01-12T01:44:00.295Z","count":0,"uniques":0},{"timestamp":"2026-01-13T01:26:34.611Z","count":0,"uniques":0},{"timestamp":"2026-01-14T01:43:01.018Z","count":0,"uniques":0},{"timestamp":"2026-01-15T00:00:00.000Z","count":1,"uniques":1},{"timestamp":"2026-01-16T00:00:00.000Z","count":1,"uniques":1},{"timestamp":"2026-01-17T01:26:33.916Z","count":0,"uniques":0},{"timestamp":"2026-01-18T00:00:00.000Z","count":1,"uniques":1},{"timestamp":"2026-01-19T01:44:33.704Z","count":0,"uniques":0},{"timestamp":"2026-01-20T01:39:42.316Z","count":0,"uniques":0}]
