[{"timestamp":"2025-12-29T01:44:32.911Z","count":0,"uniques":0},{"timestamp":"2025-12-30T01:27:49.382Z","count":0,"uniques":0},{"timestamp":"2025-12-31T00:00:00.000Z","count":3,"uniques":1},{"timestamp":"2026-01-01T00:00:00.000Z","count":1,"uniques":1},{"timestamp":"2026-01-02T00:00:00.000Z","count":1,"uniques":1},{"timestamp":"2026-01-03T00:00:00.000Z","count":1,"uniques":1},{"timestamp":"2026-01-04T01:47:13.708Z","count":0,"uniques":0},{"timestamp":"2026-01-05T01:47:08.567Z","count":0,"uniques":0}]
