[{"timestamp":"2025-08-08T01:43:36.720Z","count":0,"uniques":0},{"timestamp":"2025-08-09T01:26:33.844Z","count":0,"uniques":0},{"timestamp":"2025-08-10T01:47:07.555Z","count":0,"uniques":0},{"timestamp":"2025-08-11T01:44:08.499Z","count":0,"uniques":0},{"timestamp":"2025-08-12T01:25:48.783Z","count":0,"uniques":0},{"timestamp":"2025-08-13T01:27:20.050Z","count":0,"uniques":0},{"timestamp":"2025-08-14T01:27:29.178Z","count":0,"uniques":0},{"timestamp":"2025-08-15T01:27:57.562Z","count":0,"uniques":0}]
