[{"timestamp":"2025-05-20T01:24:57.935Z","count":0,"uniques":0},{"timestamp":"2025-05-21T01:24:35.654Z","count":0,"uniques":0},{"timestamp":"2025-05-22T01:23:42.165Z","count":0,"uniques":0},{"timestamp":"2025-05-23T01:23:58.794Z","count":0,"uniques":0},{"timestamp":"2025-05-24T01:21:07.098Z","count":0,"uniques":0},{"timestamp":"2025-05-25T01:38:56.669Z","count":0,"uniques":0},{"timestamp":"2025-05-26T01:26:01.353Z","count":0,"uniques":0},{"timestamp":"2025-05-27T01:23:07.530Z","count":0,"uniques":0}]
