[{"timestamp":"2025-01-26T01:12:10.535Z","count":0,"uniques":0},{"timestamp":"2025-01-27T01:11:43.824Z","count":0,"uniques":0},{"timestamp":"2025-01-28T01:09:52.740Z","count":0,"uniques":0},{"timestamp":"2025-01-29T01:09:42.369Z","count":0,"uniques":0},{"timestamp":"2025-01-30T01:09:02.844Z","count":0,"uniques":0},{"timestamp":"2025-01-31T01:10:12.282Z","count":0,"uniques":0},{"timestamp":"2025-02-01T01:13:54.807Z","count":0,"uniques":0},{"timestamp":"2025-02-02T01:13:32.087Z","count":0,"uniques":0}]
