[{"timestamp":"2025-01-17T01:09:22.663Z","count":0,"uniques":0},{"timestamp":"2025-01-18T01:07:34.113Z","count":0,"uniques":0},{"timestamp":"2025-01-19T01:14:49.463Z","count":0,"uniques":0},{"timestamp":"2025-01-20T01:11:19.453Z","count":0,"uniques":0},{"timestamp":"2025-01-21T01:09:34.844Z","count":0,"uniques":0},{"timestamp":"2025-01-22T01:11:19.132Z","count":0,"uniques":0},{"timestamp":"2025-01-23T01:09:54.795Z","count":0,"uniques":0},{"timestamp":"2025-01-24T01:10:18.604Z","count":0,"uniques":0}]
