[{"timestamp":"2024-05-04T00:56:21.851Z","count":0,"uniques":0},{"timestamp":"2024-05-05T01:00:40.932Z","count":0,"uniques":0},{"timestamp":"2024-05-06T00:58:26.721Z","count":0,"uniques":0},{"timestamp":"2024-05-07T00:57:24.221Z","count":0,"uniques":0},{"timestamp":"2024-05-08T00:47:47.056Z","count":0,"uniques":0},{"timestamp":"2024-05-09T00:57:34.971Z","count":0,"uniques":0},{"timestamp":"2024-05-10T00:00:00.000Z","count":1,"uniques":1},{"timestamp":"2024-05-11T00:57:09.763Z","count":0,"uniques":0},{"timestamp":"2024-05-12T01:02:20.892Z","count":0,"uniques":0},{"timestamp":"2024-05-13T00:59:14.790Z","count":0,"uniques":0},{"timestamp":"2024-05-14T00:58:18.847Z","count":0,"uniques":0},{"timestamp":"2024-05-15T00:58:32.904Z","count":0,"uniques":0},{"timestamp":"2024-05-16T00:58:35.106Z","count":0,"uniques":0},{"timestamp":"2024-05-17T00:58:33.151Z","count":0,"uniques":0},{"timestamp":"2024-05-18T00:57:48.423Z","count":0,"uniques":0},{"timestamp":"2024-05-19T01:02:50.752Z","count":0,"uniques":0},{"timestamp":"2024-05-20T00:59:04.710Z","count":0,"uniques":0},{"timestamp":"2024-05-21T00:58:31.577Z","count":0,"uniques":0},{"timestamp":"2024-05-22T00:59:17.309Z","count":0,"uniques":0},{"timestamp":"2024-05-23T00:58:23.156Z","count":0,"uniques":0},{"timestamp":"2024-05-24T00:58:54.580Z","count":0,"uniques":0},{"timestamp":"2024-05-25T00:57:46.413Z","count":0,"uniques":0},{"timestamp":"2024-05-26T01:03:28.451Z","count":0,"uniques":0},{"timestamp":"2024-05-27T01:00:17.425Z","count":0,"uniques":0},{"timestamp":"2024-05-28T00:59:08.968Z","count":0,"uniques":0},{"timestamp":"2024-05-29T01:02:28.517Z","count":0,"uniques":0},{"timestamp":"2024-05-30T00:59:34.584Z","count":0,"uniques":0},{"timestamp":"2024-05-31T01:00:17.126Z","count":0,"uniques":0},{"timestamp":"2024-06-01T01:03:13.429Z","count":0,"uniques":0},{"timestamp":"2024-06-02T01:03:32.603Z","count":0,"uniques":0},{"timestamp":"2024-06-03T01:00:48.659Z","count":0,"uniques":0},{"timestamp":"2024-06-04T01:00:24.011Z","count":0,"uniques":0},{"timestamp":"2024-06-05T01:00:04.240Z","count":0,"uniques":0},{"timestamp":"2024-06-06T00:59:54.144Z","count":0,"uniques":0},{"timestamp":"2024-06-07T01:02:26.057Z","count":0,"uniques":0},{"timestamp":"2024-06-08T01:00:08.330Z","count":0,"uniques":0},{"timestamp":"2024-06-09T01:05:43.872Z","count":0,"uniques":0},{"timestamp":"2024-06-10T01:02:29.278Z","count":0,"uniques":0},{"timestamp":"2024-06-11T01:01:14.527Z","count":0,"uniques":0},{"timestamp":"2024-06-12T01:01:10.861Z","count":0,"uniques":0},{"timestamp":"2024-06-13T01:00:45.134Z","count":0,"uniques":0},{"timestamp":"2024-06-14T01:00:50.596Z","count":0,"uniques":0},{"timestamp":"2024-06-15T01:00:45.030Z","count":0,"uniques":0},{"timestamp":"2024-06-16T01:05:40.468Z","count":0,"uniques":0},{"timestamp":"2024-06-17T01:02:58.305Z","count":0,"uniques":0},{"timestamp":"2024-06-18T01:01:24.173Z","count":0,"uniques":0},{"timestamp":"2024-06-19T01:01:42.878Z","count":0,"uniques":0},{"timestamp":"2024-06-20T00:59:51.988Z","count":0,"uniques":0},{"timestamp":"2024-06-21T01:00:20.712Z","count":0,"uniques":0},{"timestamp":"2024-06-22T00:59:59.270Z","count":0,"uniques":0},{"timestamp":"2024-06-23T01:05:00.678Z","count":0,"uniques":0},{"timestamp":"2024-06-24T01:02:38.633Z","count":0,"uniques":0},{"timestamp":"2024-06-25T01:01:01.246Z","count":0,"uniques":0},{"timestamp":"2024-06-26T01:01:13.365Z","count":0,"uniques":0},{"timestamp":"2024-06-27T01:01:27.343Z","count":0,"uniques":0},{"timestamp":"2024-06-28T01:01:23.192Z","count":0,"uniques":0},{"timestamp":"2024-06-29T01:00:17.447Z","count":0,"uniques":0},{"timestamp":"2024-06-30T01:06:36.943Z","count":0,"uniques":0},{"timestamp":"2024-07-01T01:08:37.167Z","count":0,"uniques":0},{"timestamp":"2024-07-02T01:01:47.414Z","count":0,"uniques":0},{"timestamp":"2024-07-03T01:01:37.679Z","count":0,"uniques":0},{"timestamp":"2024-07-04T01:01:45.703Z","count":0,"uniques":0},{"timestamp":"2024-07-05T01:01:39.667Z","count":0,"uniques":0},{"timestamp":"2024-07-06T01:00:11.875Z","count":0,"uniques":0},{"timestamp":"2024-07-07T01:07:03.703Z","count":0,"uniques":0},{"timestamp":"2024-07-08T01:03:44.186Z","count":0,"uniques":0},{"timestamp":"2024-07-09T01:02:39.778Z","count":0,"uniques":0},{"timestamp":"2024-07-10T01:03:14.859Z","count":0,"uniques":0},{"timestamp":"2024-07-11T01:03:15.651Z","count":0,"uniques":0},{"timestamp":"2024-07-12T01:02:01.136Z","count":0,"uniques":0},{"timestamp":"2024-07-13T01:03:02.464Z","count":0,"uniques":0},{"timestamp":"2024-07-14T01:07:53.447Z","count":0,"uniques":0},{"timestamp":"2024-07-15T01:04:51.926Z","count":0,"uniques":0},{"timestamp":"2024-07-16T01:04:05.101Z","count":0,"uniques":0},{"timestamp":"2024-07-17T01:03:24.206Z","count":0,"uniques":0},{"timestamp":"2024-07-18T01:02:20.315Z","count":0,"uniques":0},{"timestamp":"2024-07-19T10:36:08.388Z","count":0,"uniques":0},{"timestamp":"2024-07-20T01:01:54.977Z","count":0,"uniques":0},{"timestamp":"2024-07-21T01:07:51.852Z","count":0,"uniques":0},{"timestamp":"2024-07-22T01:05:19.813Z","count":0,"uniques":0},{"timestamp":"2024-07-23T01:03:26.643Z","count":0,"uniques":0},{"timestamp":"2024-07-24T01:04:08.683Z","count":0,"uniques":0},{"timestamp":"2024-07-25T01:03:37.368Z","count":0,"uniques":0},{"timestamp":"2024-07-26T01:02:42.089Z","count":0,"uniques":0},{"timestamp":"2024-07-27T01:02:26.473Z","count":0,"uniques":0},{"timestamp":"2024-07-28T01:08:05.552Z","count":0,"uniques":0},{"timestamp":"2024-07-29T01:05:06.302Z","count":0,"uniques":0},{"timestamp":"2024-07-30T01:03:42.637Z","count":0,"uniques":0},{"timestamp":"2024-07-31T00:53:24.072Z","count":0,"uniques":0},{"timestamp":"2024-08-01T01:09:06.332Z","count":0,"uniques":0},{"timestamp":"2024-08-02T01:03:21.891Z","count":0,"uniques":0},{"timestamp":"2024-08-03T01:02:46.571Z","count":0,"uniques":0},{"timestamp":"2024-08-04T01:08:22.290Z","count":0,"uniques":0},{"timestamp":"2024-08-05T01:05:32.773Z","count":0,"uniques":0},{"timestamp":"2024-08-06T01:03:44.321Z","count":0,"uniques":0},{"timestamp":"2024-08-07T01:04:32.809Z","count":0,"uniques":0},{"timestamp":"2024-08-08T01:04:33.513Z","count":0,"uniques":0},{"timestamp":"2024-08-09T01:05:08.008Z","count":0,"uniques":0},{"timestamp":"2024-08-10T01:04:55.503Z","count":0,"uniques":0},{"timestamp":"2024-08-11T01:09:42.864Z","count":0,"uniques":0},{"timestamp":"2024-08-12T01:06:18.185Z","count":0,"uniques":0},{"timestamp":"2024-08-13T01:05:45.662Z","count":0,"uniques":0},{"timestamp":"2024-08-14T01:04:43.734Z","count":0,"uniques":0},{"timestamp":"2024-08-15T01:01:45.300Z","count":0,"uniques":0},{"timestamp":"2024-08-16T01:04:10.403Z","count":0,"uniques":0},{"timestamp":"2024-08-17T01:02:19.909Z","count":0,"uniques":0},{"timestamp":"2024-08-18T01:08:28.787Z","count":0,"uniques":0},{"timestamp":"2024-08-19T01:05:14.359Z","count":0,"uniques":0},{"timestamp":"2024-08-20T01:04:13.044Z","count":0,"uniques":0},{"timestamp":"2024-08-21T01:04:27.284Z","count":0,"uniques":0},{"timestamp":"2024-08-22T01:05:44.265Z","count":0,"uniques":0},{"timestamp":"2024-08-23T01:04:56.148Z","count":0,"uniques":0},{"timestamp":"2024-08-24T01:03:29.585Z","count":0,"uniques":0},{"timestamp":"2024-08-25T01:10:20.433Z","count":0,"uniques":0},{"timestamp":"2024-08-26T01:05:25.062Z","count":0,"uniques":0},{"timestamp":"2024-08-27T01:05:54.360Z","count":0,"uniques":0},{"timestamp":"2024-08-28T01:06:35.757Z","count":0,"uniques":0},{"timestamp":"2024-08-29T01:07:06.344Z","count":0,"uniques":0},{"timestamp":"2024-08-30T01:07:24.393Z","count":0,"uniques":0},{"timestamp":"2024-08-31T01:06:55.592Z","count":0,"uniques":0},{"timestamp":"2024-09-01T01:17:46.358Z","count":0,"uniques":0},{"timestamp":"2024-09-02T01:08:57.873Z","count":0,"uniques":0},{"timestamp":"2024-09-03T01:06:43.455Z","count":0,"uniques":0},{"timestamp":"2024-09-04T01:07:28.827Z","count":0,"uniques":0},{"timestamp":"2024-09-05T01:07:32.074Z","count":0,"uniques":0},{"timestamp":"2024-09-06T01:07:27.287Z","count":0,"uniques":0},{"timestamp":"2024-09-07T01:06:22.073Z","count":0,"uniques":0},{"timestamp":"2024-09-08T01:13:10.017Z","count":0,"uniques":0},{"timestamp":"2024-09-09T01:09:59.983Z","count":0,"uniques":0},{"timestamp":"2024-09-10T01:08:38.552Z","count":0,"uniques":0},{"timestamp":"2024-09-11T01:07:55.141Z","count":0,"uniques":0},{"timestamp":"2024-09-12T01:07:55.741Z","count":0,"uniques":0},{"timestamp":"2024-09-13T01:08:24.483Z","count":0,"uniques":0},{"timestamp":"2024-09-14T01:07:23.549Z","count":0,"uniques":0},{"timestamp":"2024-09-15T01:15:38.923Z","count":0,"uniques":0},{"timestamp":"2024-09-16T01:12:50.105Z","count":0,"uniques":0},{"timestamp":"2024-09-17T00:57:11.905Z","count":0,"uniques":0},{"timestamp":"2024-09-18T01:08:17.708Z","count":0,"uniques":0},{"timestamp":"2024-09-19T01:09:40.139Z","count":0,"uniques":0},{"timestamp":"2024-09-20T01:09:30.626Z","count":0,"uniques":0},{"timestamp":"2024-09-21T01:08:11.136Z","count":0,"uniques":0},{"timestamp":"2024-09-22T01:16:03.911Z","count":0,"uniques":0},{"timestamp":"2024-09-23T01:11:39.729Z","count":0,"uniques":0},{"timestamp":"2024-09-24T01:11:45.904Z","count":0,"uniques":0},{"timestamp":"2024-09-25T01:12:45.022Z","count":0,"uniques":0},{"timestamp":"2024-09-26T01:11:11.195Z","count":0,"uniques":0},{"timestamp":"2024-09-27T01:11:50.804Z","count":0,"uniques":0},{"timestamp":"2024-09-28T01:11:14.167Z","count":0,"uniques":0},{"timestamp":"2024-09-29T01:16:58.591Z","count":0,"uniques":0},{"timestamp":"2024-09-30T01:13:51.299Z","count":0,"uniques":0},{"timestamp":"2024-10-01T01:18:21.535Z","count":0,"uniques":0},{"timestamp":"2024-10-02T01:11:38.074Z","count":0,"uniques":0},{"timestamp":"2024-10-03T01:12:01.356Z","count":0,"uniques":0},{"timestamp":"2024-10-04T01:11:38.844Z","count":0,"uniques":0},{"timestamp":"2024-10-05T01:10:37.780Z","count":0,"uniques":0},{"timestamp":"2024-10-06T01:16:30.907Z","count":0,"uniques":0},{"timestamp":"2024-10-07T01:13:36.764Z","count":0,"uniques":0},{"timestamp":"2024-10-08T01:11:27.953Z","count":0,"uniques":0},{"timestamp":"2024-10-09T01:11:12.040Z","count":0,"uniques":0},{"timestamp":"2024-10-10T01:11:07.450Z","count":0,"uniques":0},{"timestamp":"2024-10-11T01:11:27.976Z","count":0,"uniques":0},{"timestamp":"2024-10-12T01:09:50.977Z","count":0,"uniques":0},{"timestamp":"2024-10-13T01:16:22.685Z","count":0,"uniques":0},{"timestamp":"2024-10-14T01:13:41.402Z","count":0,"uniques":0},{"timestamp":"2024-10-15T01:12:44.213Z","count":0,"uniques":0},{"timestamp":"2024-10-16T01:12:36.542Z","count":0,"uniques":0},{"timestamp":"2024-10-17T01:11:39.395Z","count":0,"uniques":0},{"timestamp":"2024-10-18T01:12:01.948Z","count":0,"uniques":0},{"timestamp":"2024-10-19T01:11:12.446Z","count":0,"uniques":0},{"timestamp":"2024-10-20T01:17:39.441Z","count":0,"uniques":0},{"timestamp":"2024-10-21T01:13:46.981Z","count":0,"uniques":0},{"timestamp":"2024-10-22T01:12:45.317Z","count":0,"uniques":0},{"timestamp":"2024-10-23T01:11:22.310Z","count":0,"uniques":0},{"timestamp":"2024-10-24T01:12:04.840Z","count":0,"uniques":0},{"timestamp":"2024-10-25T01:12:38.308Z","count":0,"uniques":0},{"timestamp":"2024-10-26T01:10:21.024Z","count":0,"uniques":0},{"timestamp":"2024-10-27T01:17:19.742Z","count":0,"uniques":0},{"timestamp":"2024-10-28T01:15:03.010Z","count":0,"uniques":0},{"timestamp":"2024-10-29T01:13:38.638Z","count":0,"uniques":0},{"timestamp":"2024-10-30T01:12:52.471Z","count":0,"uniques":0},{"timestamp":"2024-10-31T01:13:19.376Z","count":0,"uniques":0},{"timestamp":"2024-11-01T01:17:43.047Z","count":0,"uniques":0},{"timestamp":"2024-11-02T01:11:03.921Z","count":0,"uniques":0},{"timestamp":"2024-11-03T01:17:01.362Z","count":0,"uniques":0},{"timestamp":"2024-11-04T01:14:01.989Z","count":0,"uniques":0},{"timestamp":"2024-11-05T01:10:42.734Z","count":0,"uniques":0},{"timestamp":"2024-11-06T01:10:38.348Z","count":0,"uniques":0},{"timestamp":"2024-11-07T01:10:50.958Z","count":0,"uniques":0},{"timestamp":"2024-11-08T01:11:18.114Z","count":0,"uniques":0},{"timestamp":"2024-11-09T01:09:03.762Z","count":0,"uniques":0},{"timestamp":"2024-11-10T01:15:15.340Z","count":0,"uniques":0},{"timestamp":"2024-11-11T01:12:29.228Z","count":0,"uniques":0},{"timestamp":"2024-11-12T01:10:18.692Z","count":0,"uniques":0},{"timestamp":"2024-11-13T01:11:28.877Z","count":0,"uniques":0},{"timestamp":"2024-11-14T01:11:47.847Z","count":0,"uniques":0},{"timestamp":"2024-11-15T01:16:00.109Z","count":0,"uniques":0},{"timestamp":"2024-11-16T01:14:14.481Z","count":0,"uniques":0},{"timestamp":"2024-11-17T01:19:23.112Z","count":0,"uniques":0},{"timestamp":"2024-11-18T01:17:16.145Z","count":0,"uniques":0},{"timestamp":"2024-11-19T01:15:54.727Z","count":0,"uniques":0},{"timestamp":"2024-11-20T01:15:15.262Z","count":0,"uniques":0},{"timestamp":"2024-11-21T01:15:12.865Z","count":0,"uniques":0},{"timestamp":"2024-11-22T01:15:52.897Z","count":0,"uniques":0},{"timestamp":"2024-11-23T01:12:57.234Z","count":0,"uniques":0},{"timestamp":"2024-11-24T01:20:07.756Z","count":0,"uniques":0},{"timestamp":"2024-11-25T01:17:01.816Z","count":0,"uniques":0},{"timestamp":"2024-11-26T01:16:17.570Z","count":0,"uniques":0},{"timestamp":"2024-11-27T01:17:39.857Z","count":0,"uniques":0},{"timestamp":"2024-11-28T01:17:03.547Z","count":0,"uniques":0},{"timestamp":"2024-11-29T01:17:10.348Z","count":0,"uniques":0},{"timestamp":"2024-11-30T01:15:03.531Z","count":0,"uniques":0},{"timestamp":"2024-12-01T01:28:56.168Z","count":0,"uniques":0},{"timestamp":"2024-12-02T01:19:39.075Z","count":0,"uniques":0},{"timestamp":"2024-12-03T01:18:36.146Z","count":0,"uniques":0},{"timestamp":"2024-12-04T01:18:38.840Z","count":0,"uniques":0},{"timestamp":"2024-12-05T01:18:48.707Z","count":0,"uniques":0},{"timestamp":"2024-12-06T01:17:51.961Z","count":0,"uniques":0},{"timestamp":"2024-12-07T01:17:16.681Z","count":0,"uniques":0},{"timestamp":"2024-12-08T01:23:52.996Z","count":0,"uniques":0},{"timestamp":"2024-12-09T01:20:34.956Z","count":0,"uniques":0},{"timestamp":"2024-12-10T01:19:33.819Z","count":0,"uniques":0},{"timestamp":"2024-12-11T01:18:32.708Z","count":0,"uniques":0},{"timestamp":"2024-12-12T01:18:13.893Z","count":0,"uniques":0},{"timestamp":"2024-12-13T01:19:17.193Z","count":0,"uniques":0},{"timestamp":"2024-12-14T01:16:07.801Z","count":0,"uniques":0},{"timestamp":"2024-12-15T01:23:46.504Z","count":0,"uniques":0},{"timestamp":"2024-12-16T01:20:59.728Z","count":0,"uniques":0},{"timestamp":"2024-12-17T01:18:30.703Z","count":0,"uniques":0},{"timestamp":"2024-12-18T01:15:19.026Z","count":0,"uniques":0},{"timestamp":"2024-12-19T01:16:14.405Z","count":0,"uniques":0},{"timestamp":"2024-12-20T01:12:51.513Z","count":0,"uniques":0},{"timestamp":"2024-12-21T01:11:13.029Z","count":0,"uniques":0},{"timestamp":"2024-12-22T01:17:44.312Z","count":0,"uniques":0},{"timestamp":"2024-12-23T01:13:47.978Z","count":0,"uniques":0},{"timestamp":"2024-12-24T01:12:12.098Z","count":0,"uniques":0},{"timestamp":"2024-12-25T01:11:41.377Z","count":0,"uniques":0},{"timestamp":"2024-12-26T01:11:36.727Z","count":0,"uniques":0},{"timestamp":"2024-12-27T01:11:57.447Z","count":0,"uniques":0},{"timestamp":"2024-12-28T01:10:36.346Z","count":0,"uniques":0},{"timestamp":"2024-12-29T01:18:25.671Z","count":0,"uniques":0},{"timestamp":"2024-12-30T01:14:25.393Z","count":0,"uniques":0},{"timestamp":"2024-12-31T01:11:52.759Z","count":0,"uniques":0},{"timestamp":"2025-01-01T01:18:09.423Z","count":0,"uniques":0},{"timestamp":"2025-01-02T01:11:25.883Z","count":0,"uniques":0},{"timestamp":"2025-01-03T01:12:20.209Z","count":0,"uniques":0},{"timestamp":"2025-01-04T01:10:48.640Z","count":0,"uniques":0},{"timestamp":"2025-01-05T01:18:08.850Z","count":0,"uniques":0},{"timestamp":"2025-01-06T01:15:27.021Z","count":0,"uniques":0},{"timestamp":"2025-01-07T01:13:06.033Z","count":0,"uniques":0},{"timestamp":"2025-01-08T01:12:48.671Z","count":0,"uniques":0},{"timestamp":"2025-01-09T01:12:07.235Z","count":0,"uniques":0},{"timestamp":"2025-01-10T01:14:22.309Z","count":0,"uniques":0},{"timestamp":"2025-01-11T01:12:44.505Z","count":0,"uniques":0},{"timestamp":"2025-01-12T01:18:56.075Z","count":0,"uniques":0},{"timestamp":"2025-01-13T01:16:10.081Z","count":0,"uniques":0},{"timestamp":"2025-01-14T00:00:00.000Z","count":1,"uniques":1},{"timestamp":"2025-01-15T01:10:47.379Z","count":0,"uniques":0},{"timestamp":"2025-01-16T01:10:16.882Z","count":0,"uniques":0},{"timestamp":"2025-01-17T01:09:56.821Z","count":0,"uniques":0},{"timestamp":"2025-01-18T01:08:07.846Z","count":0,"uniques":0},{"timestamp":"2025-01-19T01:15:23.269Z","count":0,"uniques":0},{"timestamp":"2025-01-20T01:11:57.391Z","count":0,"uniques":0},{"timestamp":"2025-01-21T01:10:08.997Z","count":0,"uniques":0},{"timestamp":"2025-01-22T01:11:53.527Z","count":0,"uniques":0},{"timestamp":"2025-01-23T01:10:29.863Z","count":0,"uniques":0},{"timestamp":"2025-01-24T01:10:53.833Z","count":0,"uniques":0},{"timestamp":"2025-01-25T01:06:54.417Z","count":0,"uniques":0},{"timestamp":"2025-01-26T01:12:44.618Z","count":0,"uniques":0},{"timestamp":"2025-01-27T01:12:16.607Z","count":0,"uniques":0},{"timestamp":"2025-01-28T01:10:27.689Z","count":0,"uniques":0},{"timestamp":"2025-01-29T01:10:17.054Z","count":0,"uniques":0},{"timestamp":"2025-01-30T01:09:37.113Z","count":0,"uniques":0},{"timestamp":"2025-01-31T01:10:46.343Z","count":0,"uniques":0},{"timestamp":"2025-02-01T01:14:28.886Z","count":0,"uniques":0},{"timestamp":"2025-02-02T01:14:06.841Z","count":0,"uniques":0},{"timestamp":"2025-02-03T01:11:54.633Z","count":0,"uniques":0},{"timestamp":"2025-02-04T01:10:47.585Z","count":0,"uniques":0},{"timestamp":"2025-02-05T01:11:52.928Z","count":0,"uniques":0},{"timestamp":"2025-02-06T01:11:53.278Z","count":0,"uniques":0},{"timestamp":"2025-02-07T01:11:55.977Z","count":0,"uniques":0},{"timestamp":"2025-02-08T01:09:52.406Z","count":0,"uniques":0},{"timestamp":"2025-02-09T01:15:29.216Z","count":0,"uniques":0},{"timestamp":"2025-02-10T01:12:49.874Z","count":0,"uniques":0},{"timestamp":"2025-02-11T01:11:27.140Z","count":0,"uniques":0},{"timestamp":"2025-02-12T01:11:54.603Z","count":0,"uniques":0},{"timestamp":"2025-02-13T01:12:14.742Z","count":0,"uniques":0},{"timestamp":"2025-02-14T01:11:57.269Z","count":0,"uniques":0},{"timestamp":"2025-02-15T01:10:58.406Z","count":0,"uniques":0},{"timestamp":"2025-02-16T01:17:33.774Z","count":0,"uniques":0},{"timestamp":"2025-02-17T01:14:43.205Z","count":0,"uniques":0},{"timestamp":"2025-02-18T01:12:02.636Z","count":0,"uniques":0},{"timestamp":"2025-02-19T01:12:27.834Z","count":0,"uniques":0},{"timestamp":"2025-02-20T01:12:40.761Z","count":0,"uniques":0},{"timestamp":"2025-02-21T01:13:01.907Z","count":0,"uniques":0},{"timestamp":"2025-02-22T01:10:48.819Z","count":0,"uniques":0},{"timestamp":"2025-02-23T01:17:30.968Z","count":0,"uniques":0},{"timestamp":"2025-02-24T01:14:41.693Z","count":0,"uniques":0},{"timestamp":"2025-02-25T01:14:07.554Z","count":0,"uniques":0},{"timestamp":"2025-02-26T01:13:47.414Z","count":0,"uniques":0},{"timestamp":"2025-02-27T01:13:59.902Z","count":0,"uniques":0},{"timestamp":"2025-02-28T01:14:22.146Z","count":0,"uniques":0},{"timestamp":"2025-03-01T01:18:54.342Z","count":0,"uniques":0},{"timestamp":"2025-03-02T01:18:14.551Z","count":0,"uniques":0},{"timestamp":"2025-03-03T01:16:25.545Z","count":0,"uniques":0},{"timestamp":"2025-03-04T01:14:56.186Z","count":0,"uniques":0},{"timestamp":"2025-03-05T01:15:07.743Z","count":0,"uniques":0},{"timestamp":"2025-03-06T01:15:18.992Z","count":0,"uniques":0},{"timestamp":"2025-03-07T01:15:49.809Z","count":0,"uniques":0},{"timestamp":"2025-03-08T01:00:13.303Z","count":0,"uniques":0},{"timestamp":"2025-03-09T01:05:42.201Z","count":0,"uniques":0},{"timestamp":"2025-03-10T01:03:47.306Z","count":0,"uniques":0},{"timestamp":"2025-03-11T01:15:42.362Z","count":0,"uniques":0},{"timestamp":"2025-03-12T01:15:04.792Z","count":0,"uniques":0},{"timestamp":"2025-03-13T01:16:20.686Z","count":0,"uniques":0},{"timestamp":"2025-03-14T01:14:59.113Z","count":0,"uniques":0},{"timestamp":"2025-03-15T01:14:14.930Z","count":0,"uniques":0},{"timestamp":"2025-03-16T01:20:54.473Z","count":0,"uniques":0},{"timestamp":"2025-03-17T01:18:24.483Z","count":0,"uniques":0},{"timestamp":"2025-03-18T01:15:55.719Z","count":0,"uniques":0},{"timestamp":"2025-03-19T01:16:49.059Z","count":0,"uniques":0},{"timestamp":"2025-03-20T01:15:40.315Z","count":0,"uniques":0},{"timestamp":"2025-03-21T01:17:02.652Z","count":0,"uniques":0},{"timestamp":"2025-03-22T01:15:16.471Z","count":0,"uniques":0},{"timestamp":"2025-03-23T01:21:31.317Z","count":0,"uniques":0},{"timestamp":"2025-03-24T01:19:11.696Z","count":0,"uniques":0},{"timestamp":"2025-03-25T01:17:53.236Z","count":0,"uniques":0},{"timestamp":"2025-03-26T01:17:12.986Z","count":0,"uniques":0},{"timestamp":"2025-03-27T01:16:49.259Z","count":0,"uniques":0},{"timestamp":"2025-03-28T01:17:00.309Z","count":0,"uniques":0},{"timestamp":"2025-03-29T01:16:14.731Z","count":0,"uniques":0},{"timestamp":"2025-03-30T01:23:00.124Z","count":0,"uniques":0},{"timestamp":"2025-03-31T01:21:08.151Z","count":0,"uniques":0},{"timestamp":"2025-04-01T01:26:18.717Z","count":0,"uniques":0},{"timestamp":"2025-04-02T01:19:23.540Z","count":0,"uniques":0},{"timestamp":"2025-04-03T01:17:26.871Z","count":0,"uniques":0},{"timestamp":"2025-04-04T01:17:19.133Z","count":0,"uniques":0},{"timestamp":"2025-04-05T01:16:23.559Z","count":0,"uniques":0},{"timestamp":"2025-04-06T01:22:12.053Z","count":0,"uniques":0},{"timestamp":"2025-04-07T01:20:03.474Z","count":0,"uniques":0},{"timestamp":"2025-04-08T01:18:00.198Z","count":0,"uniques":0},{"timestamp":"2025-04-09T01:18:03.201Z","count":0,"uniques":0},{"timestamp":"2025-04-10T01:18:03.609Z","count":0,"uniques":0},{"timestamp":"2025-04-11T01:18:31.651Z","count":0,"uniques":0},{"timestamp":"2025-04-12T01:16:44.671Z","count":0,"uniques":0},{"timestamp":"2025-04-13T02:45:56.208Z","count":0,"uniques":0},{"timestamp":"2025-04-14T01:21:22.471Z","count":0,"uniques":0},{"timestamp":"2025-04-15T01:20:33.439Z","count":0,"uniques":0},{"timestamp":"2025-04-16T01:20:06.522Z","count":0,"uniques":0},{"timestamp":"2025-04-17T01:19:07.496Z","count":0,"uniques":0},{"timestamp":"2025-04-18T01:18:14.547Z","count":0,"uniques":0},{"timestamp":"2025-04-19T01:16:03.279Z","count":0,"uniques":0},{"timestamp":"2025-04-20T01:24:37.442Z","count":0,"uniques":0},{"timestamp":"2025-04-21T01:22:57.184Z","count":0,"uniques":0},{"timestamp":"2025-04-22T01:19:42.276Z","count":0,"uniques":0},{"timestamp":"2025-04-23T01:19:42.943Z","count":0,"uniques":0},{"timestamp":"2025-04-24T01:19:55.498Z","count":0,"uniques":0},{"timestamp":"2025-04-25T01:20:49.457Z","count":0,"uniques":0},{"timestamp":"2025-04-26T01:17:36.386Z","count":0,"uniques":0},{"timestamp":"2025-04-27T01:24:45.528Z","count":0,"uniques":0},{"timestamp":"2025-04-28T01:22:35.907Z","count":0,"uniques":0},{"timestamp":"2025-04-29T01:20:36.348Z","count":0,"uniques":0},{"timestamp":"2025-04-30T01:20:38.985Z","count":0,"uniques":0},{"timestamp":"2025-05-01T01:27:27.065Z","count":0,"uniques":0},{"timestamp":"2025-05-02T01:20:56.589Z","count":0,"uniques":0},{"timestamp":"2025-05-03T01:19:04.919Z","count":0,"uniques":0},{"timestamp":"2025-05-04T01:28:16.639Z","count":0,"uniques":0}]
