[{"timestamp":"2025-11-22T01:19:20.785Z","count":0,"uniques":0},{"timestamp":"2025-11-23T01:41:32.688Z","count":0,"uniques":0},{"timestamp":"2025-11-24T01:27:57.946Z","count":0,"uniques":0},{"timestamp":"2025-11-25T01:23:09.807Z","count":0,"uniques":0},{"timestamp":"2025-11-26T01:23:17.370Z","count":0,"uniques":0},{"timestamp":"2025-11-27T01:22:03.666Z","count":0,"uniques":0},{"timestamp":"2025-11-28T01:21:13.996Z","count":0,"uniques":0},{"timestamp":"2025-11-29T01:21:24.714Z","count":0,"uniques":0}]
