[{"timestamp":"2025-12-19T01:27:53.956Z","count":0,"uniques":0},{"timestamp":"2025-12-20T01:24:05.548Z","count":0,"uniques":0},{"timestamp":"2025-12-21T01:42:29.876Z","count":0,"uniques":0},{"timestamp":"2025-12-22T01:41:56.585Z","count":0,"uniques":0},{"timestamp":"2025-12-23T01:28:05.334Z","count":0,"uniques":0},{"timestamp":"2025-12-24T01:27:07.954Z","count":0,"uniques":0},{"timestamp":"2025-12-25T01:28:13.230Z","count":0,"uniques":0},{"timestamp":"2025-12-26T01:28:24.252Z","count":0,"uniques":0}]
