[{"timestamp":"2024-10-21T01:13:06.855Z","count":0,"uniques":0},{"timestamp":"2024-10-22T01:12:05.023Z","count":0,"uniques":0},{"timestamp":"2024-10-23T01:10:42.320Z","count":0,"uniques":0},{"timestamp":"2024-10-24T01:11:20.261Z","count":0,"uniques":0},{"timestamp":"2024-10-25T01:11:58.595Z","count":0,"uniques":0},{"timestamp":"2024-10-26T01:09:41.730Z","count":0,"uniques":0},{"timestamp":"2024-10-27T01:16:36.076Z","count":0,"uniques":0},{"timestamp":"2024-10-28T01:14:22.453Z","count":0,"uniques":0}]
