[{"timestamp":"2024-02-23T00:52:43.848Z","count":0,"uniques":0},{"timestamp":"2024-02-24T00:51:21.274Z","count":0,"uniques":0},{"timestamp":"2024-02-25T00:57:07.456Z","count":0,"uniques":0},{"timestamp":"2024-02-26T00:54:36.223Z","count":0,"uniques":0},{"timestamp":"2024-02-27T00:52:43.478Z","count":0,"uniques":0},{"timestamp":"2024-02-28T00:52:49.748Z","count":0,"uniques":0},{"timestamp":"2024-02-29T00:52:58.199Z","count":0,"uniques":0},{"timestamp":"2024-03-01T00:58:24.571Z","count":0,"uniques":0}]
