[{"timestamp":"2024-09-09T01:09:20.121Z","count":0,"uniques":0},{"timestamp":"2024-09-10T01:07:58.803Z","count":0,"uniques":0},{"timestamp":"2024-09-11T01:07:15.513Z","count":0,"uniques":0},{"timestamp":"2024-09-12T01:07:16.143Z","count":0,"uniques":0},{"timestamp":"2024-09-13T01:07:44.272Z","count":0,"uniques":0},{"timestamp":"2024-09-14T01:06:44.156Z","count":0,"uniques":0},{"timestamp":"2024-09-15T01:14:59.178Z","count":0,"uniques":0},{"timestamp":"2024-09-16T01:12:08.895Z","count":0,"uniques":0}]
