[{"timestamp":"2026-02-21T01:53:56.272Z","count":0,"uniques":0},{"timestamp":"2026-02-22T02:02:12.003Z","count":0,"uniques":0},{"timestamp":"2026-02-23T02:03:36.390Z","count":0,"uniques":0},{"timestamp":"2026-02-24T01:59:51.712Z","count":0,"uniques":0},{"timestamp":"2026-02-25T02:02:11.651Z","count":0,"uniques":0},{"timestamp":"2026-02-26T01:58:14.595Z","count":0,"uniques":0},{"timestamp":"2026-02-27T01:56:50.893Z","count":0,"uniques":0},{"timestamp":"2026-02-28T01:48:01.614Z","count":0,"uniques":0}]
