[{"timestamp":"2025-02-08T01:10:40.879Z","count":0,"uniques":0},{"timestamp":"2025-02-09T01:16:16.450Z","count":0,"uniques":0},{"timestamp":"2025-02-10T01:13:38.310Z","count":0,"uniques":0},{"timestamp":"2025-02-11T01:12:14.199Z","count":0,"uniques":0},{"timestamp":"2025-02-12T01:12:46.939Z","count":0,"uniques":0},{"timestamp":"2025-02-13T01:13:02.743Z","count":0,"uniques":0},{"timestamp":"2025-02-14T01:12:46.533Z","count":0,"uniques":0},{"timestamp":"2025-02-15T01:11:46.312Z","count":0,"uniques":0}]
