[{"timestamp":"2024-07-20T01:02:05.228Z","count":0,"uniques":0},{"timestamp":"2024-07-21T01:08:01.797Z","count":0,"uniques":0},{"timestamp":"2024-07-22T01:05:29.676Z","count":0,"uniques":0},{"timestamp":"2024-07-23T01:03:37.266Z","count":0,"uniques":0},{"timestamp":"2024-07-24T01:04:18.359Z","count":0,"uniques":0},{"timestamp":"2024-07-25T01:03:47.185Z","count":0,"uniques":0},{"timestamp":"2024-07-26T01:02:51.527Z","count":0,"uniques":0},{"timestamp":"2024-07-27T01:02:36.085Z","count":0,"uniques":0}]
