[{"timestamp":"2024-03-11T00:55:43.951Z","count":0,"uniques":0},{"timestamp":"2024-03-12T00:54:12.150Z","count":0,"uniques":0},{"timestamp":"2024-03-13T00:55:11.487Z","count":0,"uniques":0},{"timestamp":"2024-03-14T00:54:32.349Z","count":0,"uniques":0},{"timestamp":"2024-03-15T00:55:04.769Z","count":0,"uniques":0},{"timestamp":"2024-03-16T00:53:34.164Z","count":0,"uniques":0},{"timestamp":"2024-03-17T00:57:58.107Z","count":0,"uniques":0},{"timestamp":"2024-03-18T00:55:42.610Z","count":0,"uniques":0}]
