[{"timestamp":"2024-08-29T01:07:11.256Z","count":0,"uniques":0},{"timestamp":"2024-08-30T01:07:29.927Z","count":0,"uniques":0},{"timestamp":"2024-08-31T01:07:00.545Z","count":0,"uniques":0},{"timestamp":"2024-09-01T01:17:51.215Z","count":0,"uniques":0},{"timestamp":"2024-09-02T01:09:02.821Z","count":0,"uniques":0},{"timestamp":"2024-09-03T01:06:48.349Z","count":0,"uniques":0},{"timestamp":"2024-09-04T01:07:33.779Z","count":0,"uniques":0},{"timestamp":"2024-09-05T01:07:37.003Z","count":0,"uniques":0}]
