[{"timestamp":"2025-12-30T01:28:53.309Z","count":0,"uniques":0},{"timestamp":"2025-12-31T01:29:50.421Z","count":0,"uniques":0},{"timestamp":"2026-01-01T01:48:14.700Z","count":0,"uniques":0},{"timestamp":"2026-01-02T01:40:17.289Z","count":0,"uniques":0},{"timestamp":"2026-01-03T01:26:01.272Z","count":0,"uniques":0},{"timestamp":"2026-01-04T01:48:17.702Z","count":0,"uniques":0},{"timestamp":"2026-01-05T01:48:10.910Z","count":0,"uniques":0},{"timestamp":"2026-01-06T01:40:14.967Z","count":0,"uniques":0}]
