[{"timestamp":"2024-08-27T01:06:39.992Z","count":0,"uniques":0},{"timestamp":"2024-08-28T01:07:20.313Z","count":0,"uniques":0},{"timestamp":"2024-08-29T01:07:50.305Z","count":0,"uniques":0},{"timestamp":"2024-08-30T01:08:13.709Z","count":0,"uniques":0},{"timestamp":"2024-08-31T01:07:39.944Z","count":0,"uniques":0},{"timestamp":"2024-09-01T01:18:30.654Z","count":0,"uniques":0},{"timestamp":"2024-09-02T01:09:42.507Z","count":0,"uniques":0},{"timestamp":"2024-09-03T01:07:27.945Z","count":0,"uniques":0}]
