[{"timestamp":"2025-05-07T01:21:53.041Z","count":0,"uniques":0},{"timestamp":"2025-05-08T01:22:25.784Z","count":0,"uniques":0},{"timestamp":"2025-05-09T01:21:43.823Z","count":0,"uniques":0},{"timestamp":"2025-05-10T01:19:09.545Z","count":0,"uniques":0},{"timestamp":"2025-05-11T01:26:45.977Z","count":0,"uniques":0},{"timestamp":"2025-05-12T01:24:44.359Z","count":0,"uniques":0},{"timestamp":"2025-05-13T01:23:02.902Z","count":0,"uniques":0},{"timestamp":"2025-05-14T01:21:58.359Z","count":0,"uniques":0}]
