[{"timestamp":"2026-07-06T03:20:43.255Z","count":0,"uniques":0},{"timestamp":"2026-07-07T02:54:03.095Z","count":0,"uniques":0},{"timestamp":"2026-07-08T02:30:53.580Z","count":0,"uniques":0},{"timestamp":"2026-07-09T02:47:58.093Z","count":0,"uniques":0},{"timestamp":"2026-07-10T02:50:44.987Z","count":0,"uniques":0},{"timestamp":"2026-07-11T02:28:36.172Z","count":0,"uniques":0},{"timestamp":"2026-07-12T02:33:58.095Z","count":0,"uniques":0},{"timestamp":"2026-07-13T02:35:39.471Z","count":0,"uniques":0}]
