[{"timestamp":"2026-01-11T01:47:34.469Z","count":0,"uniques":0},{"timestamp":"2026-01-12T01:44:10.850Z","count":0,"uniques":0},{"timestamp":"2026-01-13T01:26:44.520Z","count":0,"uniques":0},{"timestamp":"2026-01-14T01:43:10.849Z","count":0,"uniques":0},{"timestamp":"2026-01-15T01:28:28.238Z","count":0,"uniques":0},{"timestamp":"2026-01-16T01:40:16.118Z","count":0,"uniques":0},{"timestamp":"2026-01-17T01:26:43.728Z","count":0,"uniques":0},{"timestamp":"2026-01-18T01:46:11.865Z","count":0,"uniques":0}]
