[{"timestamp":"2024-11-21T01:14:39.390Z","count":0,"uniques":0},{"timestamp":"2024-11-22T01:15:23.043Z","count":0,"uniques":0},{"timestamp":"2024-11-23T01:12:27.966Z","count":0,"uniques":0},{"timestamp":"2024-11-24T01:19:34.681Z","count":0,"uniques":0},{"timestamp":"2024-11-25T01:16:31.785Z","count":0,"uniques":0},{"timestamp":"2024-11-26T01:15:47.920Z","count":0,"uniques":0},{"timestamp":"2024-11-27T01:17:07.676Z","count":0,"uniques":0},{"timestamp":"2024-11-28T01:16:33.856Z","count":0,"uniques":0},{"timestamp":"2024-11-29T01:16:41.627Z","count":0,"uniques":0},{"timestamp":"2024-11-30T01:14:35.512Z","count":0,"uniques":0},{"timestamp":"2024-12-01T01:28:26.544Z","count":0,"uniques":0},{"timestamp":"2024-12-02T01:19:09.761Z","count":0,"uniques":0},{"timestamp":"2024-12-03T01:18:07.505Z","count":0,"uniques":0},{"timestamp":"2024-12-04T01:18:10.873Z","count":0,"uniques":0},{"timestamp":"2024-12-05T01:18:18.720Z","count":0,"uniques":0},{"timestamp":"2024-12-06T01:17:19.258Z","count":0,"uniques":0},{"timestamp":"2024-12-07T01:16:48.024Z","count":0,"uniques":0},{"timestamp":"2024-12-08T01:23:24.253Z","count":0,"uniques":0},{"timestamp":"2024-12-09T01:20:05.190Z","count":0,"uniques":0},{"timestamp":"2024-12-10T01:19:04.358Z","count":0,"uniques":0},{"timestamp":"2024-12-11T01:18:03.071Z","count":0,"uniques":0},{"timestamp":"2024-12-12T01:17:44.096Z","count":0,"uniques":0},{"timestamp":"2024-12-13T01:18:48.668Z","count":0,"uniques":0},{"timestamp":"2024-12-14T01:15:38.611Z","count":0,"uniques":0},{"timestamp":"2024-12-15T01:23:16.754Z","count":0,"uniques":0},{"timestamp":"2024-12-16T01:20:29.632Z","count":0,"uniques":0},{"timestamp":"2024-12-17T01:17:57.380Z","count":0,"uniques":0},{"timestamp":"2024-12-18T01:14:49.937Z","count":0,"uniques":0},{"timestamp":"2024-12-19T01:15:45.259Z","count":0,"uniques":0},{"timestamp":"2024-12-20T01:12:21.345Z","count":0,"uniques":0},{"timestamp":"2024-12-21T01:10:44.804Z","count":0,"uniques":0}]
