[{"timestamp":"2026-01-03T01:24:41.272Z","count":0,"uniques":0},{"timestamp":"2026-01-04T01:47:03.762Z","count":0,"uniques":0},{"timestamp":"2026-01-05T01:46:59.110Z","count":0,"uniques":0},{"timestamp":"2026-01-06T01:39:03.178Z","count":0,"uniques":0},{"timestamp":"2026-01-07T01:38:46.630Z","count":0,"uniques":0},{"timestamp":"2026-01-08T01:39:05.905Z","count":0,"uniques":0},{"timestamp":"2026-01-09T01:39:27.009Z","count":0,"uniques":0},{"timestamp":"2026-01-10T01:27:07.746Z","count":0,"uniques":0}]
