[{"timestamp":"2024-06-27T01:01:42.252Z","count":0,"uniques":0},{"timestamp":"2024-06-28T01:01:37.923Z","count":0,"uniques":0},{"timestamp":"2024-06-29T01:00:31.965Z","count":0,"uniques":0},{"timestamp":"2024-06-30T01:06:51.374Z","count":0,"uniques":0},{"timestamp":"2024-07-01T01:08:52.083Z","count":0,"uniques":0},{"timestamp":"2024-07-02T01:02:02.366Z","count":0,"uniques":0},{"timestamp":"2024-07-03T01:01:52.340Z","count":0,"uniques":0},{"timestamp":"2024-07-04T01:02:01.735Z","count":0,"uniques":0}]
