[{"timestamp":"2026-04-15T02:24:46.083Z","count":0,"uniques":0},{"timestamp":"2026-04-16T02:31:44.138Z","count":0,"uniques":0},{"timestamp":"2026-04-17T02:27:41.392Z","count":0,"uniques":0},{"timestamp":"2026-04-18T02:10:44.399Z","count":0,"uniques":0},{"timestamp":"2026-04-19T02:32:34.573Z","count":0,"uniques":0},{"timestamp":"2026-04-20T02:33:22.872Z","count":0,"uniques":0},{"timestamp":"2026-04-21T02:28:51.874Z","count":0,"uniques":0},{"timestamp":"2026-04-22T02:26:56.259Z","count":0,"uniques":0}]
