[{"timestamp":"2024-10-10T01:11:32.219Z","count":0,"uniques":0},{"timestamp":"2024-10-11T01:11:53.034Z","count":0,"uniques":0},{"timestamp":"2024-10-12T01:10:15.392Z","count":0,"uniques":0},{"timestamp":"2024-10-13T01:16:47.394Z","count":0,"uniques":0},{"timestamp":"2024-10-14T01:14:05.759Z","count":0,"uniques":0},{"timestamp":"2024-10-15T01:13:07.797Z","count":0,"uniques":0},{"timestamp":"2024-10-16T01:13:01.960Z","count":0,"uniques":0},{"timestamp":"2024-10-17T01:12:03.313Z","count":0,"uniques":0}]
